jacobi/jacobiPltPrint.py
oss_pip_jacobi-0.0.2.dist-info/METADATA
oss_pip_jacobi-0.0.2.dist-info/WHEEL
oss_pip_jacobi-0.0.2.dist-info/top_level.txt
oss_pip_jacobi-0.0.2.dist-info/RECORD
