Metadata-Version: 2.1
Name: oss-pip-jacobi
Version: 0.0.2
Summary: oss-dev my jacobi 0002
Home-page: https://github.com/Kim-DO-Hyeong/jacobi0002
Download-URL: https://github.com/Kim-DO-Hyeong/jacobi0002/archive/refs/tags/v0.0.2.zip
Author: dohyeong
License: UNKNOWN
Platform: UNKNOWN
Classifier: Programming Language :: Python :: 3
